Workbook
Name CAT_SKU: 'Catalogue'!$B$7:$B$24
Name CAT_PRODUCT: 'Catalogue'!$C$7:$C$24
Name CAT_CATEGORY: 'Catalogue'!$D$7:$D$24
Name CAT_BILLING: 'Catalogue'!$E$7:$E$24
Name CAT_PRICE: 'Catalogue'!$F$7:$F$24
Name CAT_COST: 'Catalogue'!$G$7:$G$24
Name TERM: 'Quote'!$C$9
Name VAT_RATE: 'Quote'!$C$10
Name TOTAL_ONEOFF: 'Quote'!$J$24
Name TOTAL_MONTHLY: 'Quote'!$K$24
Name TOTAL_COST: 'Quote'!$L$24
Name UPFRONT_NET: 'Quote'!$D$26
Name MONTHLY_NET: 'Quote'!$D$27
Name CONTRACT_NET: 'Quote'!$D$28
Name CONTRACT_VAT: 'Quote'!$D$29
Name CONTRACT_GROSS: 'Quote'!$D$30
Name MARGIN_VALUE: 'Quote'!$D$32
Name MARGIN_PCT: 'Quote'!$D$33

Sheet Catalogue
B3: Product catalogue
B4: Feeds the dropdowns and every lookup on the Quote sheet
B6: SKU | C6: Product | D6: Category | E6: Billing | F6: Unit price | G6: Unit cost
B7: TEL-SMART-128 | C7: Smartfon biznesowy 128 GB | D7: Hardware | E7: one-off | F7: 2149 | G7: 1720
B8: TEL-SMART-256 | C8: Smartfon biznesowy 256 GB | D8: Hardware | E8: one-off | F8: 2699 | G8: 2180
B9: TEL-SMART-LT | C9: Smartfon podstawowy 64 GB | D9: Hardware | E9: one-off | F9: 1099 | G9: 860
B10: TEL-TAB-11 | C10: Tablet 11 cali LTE | D10: Hardware | E10: one-off | F10: 1849 | G10: 1490
B11: TEL-LAP-14 | C11: Laptop biznesowy 14 cali | D11: Hardware | E11: one-off | F11: 4590 | G11: 3820
B12: TEL-ROUT-5G | C12: Router 5G do biura | D12: Hardware | E12: one-off | F12: 899 | G12: 690
B13: SUB-VOICE-M | C13: Abonament głosowy bez limitu | D13: Subscription | E13: monthly | F13: 49 | G13: 28
B14: SUB-DATA-50 | C14: Pakiet danych 50 GB | D14: Subscription | E14: monthly | F14: 39 | G14: 21
B15: SUB-DATA-UNL | C15: Pakiet danych bez limitu | D15: Subscription | E15: monthly | F15: 79 | G15: 44
B16: SUB-MDM | C16: Zarządzanie flotą urządzeń (MDM) | D16: Subscription | E16: monthly | F16: 24 | G16: 11
B17: ACC-CASE | C17: Etui wzmocnione | D17: Accessory | E17: one-off | F17: 129 | G17: 62
B18: ACC-CHRG | C18: Ładowarka sieciowa 65 W | D18: Accessory | E18: one-off | F18: 189 | G18: 98
... B24: SRV-INSUR | C24: Ubezpieczenie sprzętu | D24: Service | E24: monthly | F24: 19 | G24: 9.5

Sheet Quote
B3: Quotation builder
B4: Edit the yellow cells — totals, margin and the customer page recalculate on their own
B6: Customer | C6: Kowalski Logistyka Sp. z o.o. | F6: Quote no. | H6: OFE-2026-041
B7: City | C7: Poznań | F7: Date | H7: 46229
B8: Contact person | C8: Anna Nowak | F8: Valid until | H8: 46259
B9: Contract term (months) | C9: 24 | F9: Seller | H9: Telko Partner Sp. z o.o.
B10: VAT rate | C10: 0.23
C13: Product | D13: SKU | E13: Category | F13: Billing | G13: Qty | H13: Unit price | I13: Disc. % | J13: Net one-off | K13: Net monthly | L13: Cost (contract) | M13: Margin %
C14: Smartfon biznesowy 256 GB | D14: =IFERROR(INDEX(CAT_SKU,MATCH($C14,CAT_PRODUCT,0)),"") | E14: =IFERROR(INDEX(CAT_CATEGORY,MATCH($C14,CAT_PRODUCT,0)),"") | F14: =IFERROR(INDEX(CAT_BILLING,MATCH($C14,CAT_PRODUCT,0)),"") | G14: 12 | H14: =IFERROR(INDEX(CAT_PRICE,MATCH($C14,CAT_PRODUCT,0)),0) | I14: 0.08 | J14: =IF($F14="one-off",ROUND($G14*$H14*(1-$I14),2),0) | K14: =IF($F14="monthly",ROUND($G14*$H14*(1-$I14),2),0) | L14: =IFERROR(IF($F14="monthly",$G14*INDEX(CAT_COST,MATCH($C14,CAT_PRODUCT,0))*TERM,$G14*INDEX(CAT_COST,MATCH($C14,CAT_PRODUCT,0))),0) | M14: =IFERROR(($J14+$K14*TERM-$L14)/($J14+$K14*TERM),"")
C15: Etui wzmocnione | D15: =IFERROR(INDEX(CAT_SKU,MATCH($C15,CAT_PRODUCT,0)),"") | E15: =IFERROR(INDEX(CAT_CATEGORY,MATCH($C15,CAT_PRODUCT,0)),"") | F15: =IFERROR(INDEX(CAT_BILLING,MATCH($C15,CAT_PRODUCT,0)),"") | G15: 12 | H15: =IFERROR(INDEX(CAT_PRICE,MATCH($C15,CAT_PRODUCT,0)),0) | I15: 0 | J15: =IF($F15="one-off",ROUND($G15*$H15*(1-$I15),2),0) | K15: =IF($F15="monthly",ROUND($G15*$H15*(1-$I15),2),0) | L15: =IFERROR(IF($F15="monthly",$G15*INDEX(CAT_COST,MATCH($C15,CAT_PRODUCT,0))*TERM,$G15*INDEX(CAT_COST,MATCH($C15,CAT_PRODUCT,0))),0) | M15: =IFERROR(($J15+$K15*TERM-$L15)/($J15+$K15*TERM),"")
C16: Ładowarka sieciowa 65 W | D16: =IFERROR(INDEX(CAT_SKU,MATCH($C16,CAT_PRODUCT,0)),"") | E16: =IFERROR(INDEX(CAT_CATEGORY,MATCH($C16,CAT_PRODUCT,0)),"") | F16: =IFERROR(INDEX(CAT_BILLING,MATCH($C16,CAT_PRODUCT,0)),"") | G16: 12 | H16: =IFERROR(INDEX(CAT_PRICE,MATCH($C16,CAT_PRODUCT,0)),0) | I16: 0.1 | J16: =IF($F16="one-off",ROUND($G16*$H16*(1-$I16),2),0) | K16: =IF($F16="monthly",ROUND($G16*$H16*(1-$I16),2),0) | L16: =IFERROR(IF($F16="monthly",$G16*INDEX(CAT_COST,MATCH($C16,CAT_PRODUCT,0))*TERM,$G16*INDEX(CAT_COST,MATCH($C16,CAT_PRODUCT,0))),0) | M16: =IFERROR(($J16+$K16*TERM-$L16)/($J16+$K16*TERM),"")
C17: Abonament głosowy bez limitu | D17: =IFERROR(INDEX(CAT_SKU,MATCH($C17,CAT_PRODUCT,0)),"") | E17: =IFERROR(INDEX(CAT_CATEGORY,MATCH($C17,CAT_PRODUCT,0)),"") | F17: =IFERROR(INDEX(CAT_BILLING,MATCH($C17,CAT_PRODUCT,0)),"") | G17: 12 | H17: =IFERROR(INDEX(CAT_PRICE,MATCH($C17,CAT_PRODUCT,0)),0) | I17: 0.05 | J17: =IF($F17="one-off",ROUND($G17*$H17*(1-$I17),2),0) | K17: =IF($F17="monthly",ROUND($G17*$H17*(1-$I17),2),0) | L17: =IFERROR(IF($F17="monthly",$G17*INDEX(CAT_COST,MATCH($C17,CAT_PRODUCT,0))*TERM,$G17*INDEX(CAT_COST,MATCH($C17,CAT_PRODUCT,0))),0) | M17: =IFERROR(($J17+$K17*TERM-$L17)/($J17+$K17*TERM),"")
C18: Pakiet danych 50 GB | D18: =IFERROR(INDEX(CAT_SKU,MATCH($C18,CAT_PRODUCT,0)),"") | E18: =IFERROR(INDEX(CAT_CATEGORY,MATCH($C18,CAT_PRODUCT,0)),"") | F18: =IFERROR(INDEX(CAT_BILLING,MATCH($C18,CAT_PRODUCT,0)),"") | G18: 12 | H18: =IFERROR(INDEX(CAT_PRICE,MATCH($C18,CAT_PRODUCT,0)),0) | I18: 0.05 | J18: =IF($F18="one-off",ROUND($G18*$H18*(1-$I18),2),0) | K18: =IF($F18="monthly",ROUND($G18*$H18*(1-$I18),2),0) | L18: =IFERROR(IF($F18="monthly",$G18*INDEX(CAT_COST,MATCH($C18,CAT_PRODUCT,0))*TERM,$G18*INDEX(CAT_COST,MATCH($C18,CAT_PRODUCT,0))),0) | M18: =IFERROR(($J18+$K18*TERM-$L18)/($J18+$K18*TERM),"")
C19: Zarządzanie flotą urządzeń (MDM) | D19: =IFERROR(INDEX(CAT_SKU,MATCH($C19,CAT_PRODUCT,0)),"") | E19: =IFERROR(INDEX(CAT_CATEGORY,MATCH($C19,CAT_PRODUCT,0)),"") | F19: =IFERROR(INDEX(CAT_BILLING,MATCH($C19,CAT_PRODUCT,0)),"") | G19: 12 | H19: =IFERROR(INDEX(CAT_PRICE,MATCH($C19,CAT_PRODUCT,0)),0) | I19: 0 | J19: =IF($F19="one-off",ROUND($G19*$H19*(1-$I19),2),0) | K19: =IF($F19="monthly",ROUND($G19*$H19*(1-$I19),2),0) | L19: =IFERROR(IF($F19="monthly",$G19*INDEX(CAT_COST,MATCH($C19,CAT_PRODUCT,0))*TERM,$G19*INDEX(CAT_COST,MATCH($C19,CAT_PRODUCT,0))),0) | M19: =IFERROR(($J19+$K19*TERM-$L19)/($J19+$K19*TERM),"")
C20: Laptop biznesowy 14 cali | D20: =IFERROR(INDEX(CAT_SKU,MATCH($C20,CAT_PRODUCT,0)),"") | E20: =IFERROR(INDEX(CAT_CATEGORY,MATCH($C20,CAT_PRODUCT,0)),"") | F20: =IFERROR(INDEX(CAT_BILLING,MATCH($C20,CAT_PRODUCT,0)),"") | G20: 3 | H20: =IFERROR(INDEX(CAT_PRICE,MATCH($C20,CAT_PRODUCT,0)),0) | I20: 0.06 | J20: =IF($F20="one-off",ROUND($G20*$H20*(1-$I20),2),0) | K20: =IF($F20="monthly",ROUND($G20*$H20*(1-$I20),2),0) | L20: =IFERROR(IF($F20="monthly",$G20*INDEX(CAT_COST,MATCH($C20,CAT_PRODUCT,0))*TERM,$G20*INDEX(CAT_COST,MATCH($C20,CAT_PRODUCT,0))),0) | M20: =IFERROR(($J20+$K20*TERM-$L20)/($J20+$K20*TERM),"")
C21: Stacja dokująca USB-C | D21: =IFERROR(INDEX(CAT_SKU,MATCH($C21,CAT_PRODUCT,0)),"") | E21: =IFERROR(INDEX(CAT_CATEGORY,MATCH($C21,CAT_PRODUCT,0)),"") | F21: =IFERROR(INDEX(CAT_BILLING,MATCH($C21,CAT_PRODUCT,0)),"") | G21: 3 | H21: =IFERROR(INDEX(CAT_PRICE,MATCH($C21,CAT_PRODUCT,0)),0) | I21: 0 | J21: =IF($F21="one-off",ROUND($G21*$H21*(1-$I21),2),0) | K21: =IF($F21="monthly",ROUND($G21*$H21*(1-$I21),2),0) | L21: =IFERROR(IF($F21="monthly",$G21*INDEX(CAT_COST,MATCH($C21,CAT_PRODUCT,0))*TERM,$G21*INDEX(CAT_COST,MATCH($C21,CAT_PRODUCT,0))),0) | M21: =IFERROR(($J21+$K21*TERM-$L21)/($J21+$K21*TERM),"")
C22: Wdrożenie i konfiguracja urządzeń | D22: =IFERROR(INDEX(CAT_SKU,MATCH($C22,CAT_PRODUCT,0)),"") | E22: =IFERROR(INDEX(CAT_CATEGORY,MATCH($C22,CAT_PRODUCT,0)),"") | F22: =IFERROR(INDEX(CAT_BILLING,MATCH($C22,CAT_PRODUCT,0)),"") | G22: 1 | H22: =IFERROR(INDEX(CAT_PRICE,MATCH($C22,CAT_PRODUCT,0)),0) | I22: 0 | J22: =IF($F22="one-off",ROUND($G22*$H22*(1-$I22),2),0) | K22: =IF($F22="monthly",ROUND($G22*$H22*(1-$I22),2),0) | L22: =IFERROR(IF($F22="monthly",$G22*INDEX(CAT_COST,MATCH($C22,CAT_PRODUCT,0))*TERM,$G22*INDEX(CAT_COST,MATCH($C22,CAT_PRODUCT,0))),0) | M22: =IFERROR(($J22+$K22*TERM-$L22)/($J22+$K22*TERM),"")
C23: Wsparcie techniczne SLA 8h | D23: =IFERROR(INDEX(CAT_SKU,MATCH($C23,CAT_PRODUCT,0)),"") | E23: =IFERROR(INDEX(CAT_CATEGORY,MATCH($C23,CAT_PRODUCT,0)),"") | F23: =IFERROR(INDEX(CAT_BILLING,MATCH($C23,CAT_PRODUCT,0)),"") | G23: 12 | H23: =IFERROR(INDEX(CAT_PRICE,MATCH($C23,CAT_PRODUCT,0)),0) | I23: 0 | J23: =IF($F23="one-off",ROUND($G23*$H23*(1-$I23),2),0) | K23: =IF($F23="monthly",ROUND($G23*$H23*(1-$I23),2),0) | L23: =IFERROR(IF($F23="monthly",$G23*INDEX(CAT_COST,MATCH($C23,CAT_PRODUCT,0))*TERM,$G23*INDEX(CAT_COST,MATCH($C23,CAT_PRODUCT,0))),0) | M23: =IFERROR(($J23+$K23*TERM-$L23)/($J23+$K23*TERM),"")
B24: Total | J24: =SUM(J14:J23) | K24: =SUM(K14:K23) | L24: =SUM(L14:L23)
B25: Quote summary
B26: Upfront, net (one-off items) | D26: =TOTAL_ONEOFF
B27: Recurring, net (per month) | D27: =TOTAL_MONTHLY
B28: Contract value, net | D28: =TOTAL_ONEOFF+TOTAL_MONTHLY*TERM
B29: VAT | D29: =ROUND(CONTRACT_NET*VAT_RATE,2)
B30: Contract value, gross | D30: =CONTRACT_NET+CONTRACT_VAT
B31: Cost of delivery | D31: =TOTAL_COST
B32: Gross margin | D32: =CONTRACT_NET-TOTAL_COST
B33: Gross margin % | D33: =IFERROR(MARGIN_VALUE/CONTRACT_NET,0)

Sheet Term comparison
B3: Contract term comparison
B4: The same basket priced over four terms — the selected one is marked
B6: Term (months) | C6: Upfront, net | D6: Recurring total, net | E6: Contract value, net | F6: VAT | G6: Contract value, gross | H6: Monthly if financed
B7: 12 | C7: =TOTAL_ONEOFF | D7: =TOTAL_MONTHLY*$B7 | E7: =TOTAL_ONEOFF+TOTAL_MONTHLY*$B7 | F7: =ROUND($E7*VAT_RATE,2) | G7: =$E7+$F7 | H7: =$E7/$B7 | I7: =IF($B7=TERM,"< selected term","")
B8: 24 | C8: =TOTAL_ONEOFF | D8: =TOTAL_MONTHLY*$B8 | E8: =TOTAL_ONEOFF+TOTAL_MONTHLY*$B8 | F8: =ROUND($E8*VAT_RATE,2) | G8: =$E8+$F8 | H8: =$E8/$B8 | I8: =IF($B8=TERM,"< selected term","")
B9: 36 | C9: =TOTAL_ONEOFF | D9: =TOTAL_MONTHLY*$B9 | E9: =TOTAL_ONEOFF+TOTAL_MONTHLY*$B9 | F9: =ROUND($E9*VAT_RATE,2) | G9: =$E9+$F9 | H9: =$E9/$B9 | I9: =IF($B9=TERM,"< selected term","")
B10: 48 | C10: =TOTAL_ONEOFF | D10: =TOTAL_MONTHLY*$B10 | E10: =TOTAL_ONEOFF+TOTAL_MONTHLY*$B10 | F10: =ROUND($E10*VAT_RATE,2) | G10: =$E10+$F10 | H10: =$E10/$B10 | I10: =IF($B10=TERM,"< selected term","")

Sheet Summary
B3: Quote summary
B4: Everything below is live — it follows the Quote sheet
B6: Contract value, net | D6: VAT | F6: Contract value, gross
B7: =CONTRACT_NET | D7: =CONTRACT_VAT | F7: =CONTRACT_GROSS
B9: Upfront, net | D9: Recurring, net / month | F9: Contract term (months)
B10: =UPFRONT_NET | D10: =MONTHLY_NET | F10: =TERM
B12: Cost of delivery | D12: Gross margin | F12: Gross margin %
B13: =TOTAL_COST | D13: =MARGIN_VALUE | F13: =MARGIN_PCT
B16: Metric | C16: Value
B17: Revenue (net) | C17: =CONTRACT_NET
B18: Cost | C18: =TOTAL_COST
B19: Gross margin | C19: =MARGIN_VALUE

Sheet Customer quote
B3: Quotation
B4: Print-ready page for the customer — no cost or margin data
B6: Telko Partner Sp. z o.o. | F6: Quote no. | G6: ='Quote'!$H$6
B7: ul. Przemysłowa 14, 61-441 Poznań | F7: Date | G7: ='Quote'!$H$7
B8: NIP 7792345678 | F8: Valid until | G8: ='Quote'!$H$8
B10: Prepared for
B11: ='Quote'!$C$6
B12: ='Quote'!$C$7
B13: ="Attn: "&'Quote'!$C$8
B15: # | C15: Product | D15: Billing | E15: Qty | F15: Unit price | G15: Net
B16: 1 | C16: ='Quote'!$C$14 | D16: ='Quote'!$F$14 | E16: ='Quote'!$G$14 | F16: ='Quote'!$H$14*(1-'Quote'!$I$14) | G16: ='Quote'!$J$14+'Quote'!$K$14
B17: 2 | C17: ='Quote'!$C$15 | D17: ='Quote'!$F$15 | E17: ='Quote'!$G$15 | F17: ='Quote'!$H$15*(1-'Quote'!$I$15) | G17: ='Quote'!$J$15+'Quote'!$K$15
B18: 3 | C18: ='Quote'!$C$16 | D18: ='Quote'!$F$16 | E18: ='Quote'!$G$16 | F18: ='Quote'!$H$16*(1-'Quote'!$I$16) | G18: ='Quote'!$J$16+'Quote'!$K$16
B19: 4 | C19: ='Quote'!$C$17 | D19: ='Quote'!$F$17 | E19: ='Quote'!$G$17 | F19: ='Quote'!$H$17*(1-'Quote'!$I$17) | G19: ='Quote'!$J$17+'Quote'!$K$17
B20: 5 | C20: ='Quote'!$C$18 | D20: ='Quote'!$F$18 | E20: ='Quote'!$G$18 | F20: ='Quote'!$H$18*(1-'Quote'!$I$18) | G20: ='Quote'!$J$18+'Quote'!$K$18
B21: 6 | C21: ='Quote'!$C$19 | D21: ='Quote'!$F$19 | E21: ='Quote'!$G$19 | F21: ='Quote'!$H$19*(1-'Quote'!$I$19) | G21: ='Quote'!$J$19+'Quote'!$K$19
B22: 7 | C22: ='Quote'!$C$20 | D22: ='Quote'!$F$20 | E22: ='Quote'!$G$20 | F22: ='Quote'!$H$20*(1-'Quote'!$I$20) | G22: ='Quote'!$J$20+'Quote'!$K$20
B23: 8 | C23: ='Quote'!$C$21 | D23: ='Quote'!$F$21 | E23: ='Quote'!$G$21 | F23: ='Quote'!$H$21*(1-'Quote'!$I$21) | G23: ='Quote'!$J$21+'Quote'!$K$21
B24: 9 | C24: ='Quote'!$C$22 | D24: ='Quote'!$F$22 | E24: ='Quote'!$G$22 | F24: ='Quote'!$H$22*(1-'Quote'!$I$22) | G24: ='Quote'!$J$22+'Quote'!$K$22
B25: 10 | C25: ='Quote'!$C$23 | D25: ='Quote'!$F$23 | E25: ='Quote'!$G$23 | F25: ='Quote'!$H$23*(1-'Quote'!$I$23) | G25: ='Quote'!$J$23+'Quote'!$K$23
E27: Upfront, net | G27: =UPFRONT_NET
E28: Recurring, net / month | G28: =MONTHLY_NET
E29: Contract term (months) | G29: =TERM
E30: Contract value, net | G30: =CONTRACT_NET
E31: VAT 23% | G31: =CONTRACT_VAT
E32: Contract value, gross | G32: =CONTRACT_GROSS
B35: Payment terms: 14 days from delivery, bank transfer.
B36: Recurring items are billed monthly for the length of the contract.
B37: This quotation is valid until the date shown above.
